Workbook

Sheet README
A1: Bài 02 — Tra cứu danh mục giá: XLOOKUP, VLOOKUP, HLOOKUP, INDEX/MATCH
A3: Nguồn dữ liệu | B3: Online Retail II (UCI Machine Learning Repository, Daqing Chen, 2019), https://archive.ics.uci.edu/dataset/502/online+retail+ii — giấy phép CC BY 4.0
A4: Trích mẫu | B4: Orders: 1518 dòng bán hợp lệ (không huỷ, Quantity > 0, Price > 0) của khách ngoài Anh, 01–09/12/2011, sheet 'Year 2010-2011'. Catalog: 4101 mã hàng của sheet 'Year 2009-2010' (năm trước), mô tả phổ biến nhất (đã TRIM) và giá niêm yết = giá xuất hiện nhiều nhất trên dòng hợp lệ. Regions: EU/Non-EU theo thành viên EU năm 2011.
A5: Giấy phép | B5: CC BY 4.0: được chia sẻ và chỉnh sửa, phải ghi nguồn như trên. Trích mẫu này chỉ để học.
A6: Quy ước | B6: Ô nền vàng là ô TODO: điền CÔNG THỨC (bắt đầu bằng =), không gõ số. Test đọc cả công thức lẫn giá trị.
A7: Lưu tệp | B7: LibreOffice: File > Save, chọn 'Use Excel 2007-365!' (giữ định dạng .xlsx). Excel: Ctrl+S.
A8: Chạy test | B8: uv run pytest <thư mục bài> -q (xem lệnh trong đề bài trên app)
A10: Việc cần làm | B10: 1. Sheet Orders: điền công thức hàng 2 các cột G–K (ô vàng) rồi kéo xuống hết bảng.
B11: 2. Sheet Summary: điền B2:B6 và B9 (B9 dùng INDEX/MATCH tra giá của mã nhập ở B8).
B12: 3. Lưu .xlsx rồi chạy test.

Sheet Orders
A1: Invoice | B1: InvoiceDate | C1: Country | D1: StockCode | E1: Quantity | F1: Price | G1: Description | H1: ListPrice | I1: Region | J1: LineValue | K1: DiscountPct
A2: 579901 | B2: 40878.358 | C2: Germany | D2: 22055 | E2: 8 | F2: 1.65 | G2: =_xlfn.XLOOKUP(D2,Catalog!$B$2:$B$4102,Catalog!$A$2:$A$4102,"NOT IN CATALOG") -> MINI CAKE STAND HANGING STRAWBERY | H2: =_xlfn.IFNA(VLOOKUP(D2,Catalog!$B$2:$C$4102,2,FALSE()),"") -> 1.65 | I2: =HLOOKUP(C2,Regions!$B$1:$S$2,2,FALSE()) -> EU | J2: =E2*F2 -> 13.2 | K2: =IF(H2="","",1-F2/H2) -> 0
A3: 579901 | B3: 40878.358 | C3: Germany | D3: 21232 | E3: 12 | F3: 1.25 | G3: =_xlfn.XLOOKUP(D3,Catalog!$B$2:$B$4102,Catalog!$A$2:$A$4102,"NOT IN CATALOG") -> STRAWBERRY CERAMIC TRINKET BOX | H3: =_xlfn.IFNA(VLOOKUP(D3,Catalog!$B$2:$C$4102,2,FALSE()),"") -> 1.25 | I3: =HLOOKUP(C3,Regions!$B$1:$S$2,2,FALSE()) -> EU | J3: =E3*F3 -> 15 | K3: =IF(H3="","",1-F3/H3) -> 0
A4: 579901 | B4: 40878.358 | C4: Germany | D4: 22649 | E4: 8 | F4: 4.95 | G4: =_xlfn.XLOOKUP(D4,Catalog!$B$2:$B$4102,Catalog!$A$2:$A$4102,"NOT IN CATALOG") -> STRAWBERRY FAIRY CAKE TEAPOT | H4: =_xlfn.IFNA(VLOOKUP(D4,Catalog!$B$2:$C$4102,2,FALSE()),"") -> 4.95 | I4: =HLOOKUP(C4,Regions!$B$1:$S$2,2,FALSE()) -> EU | J4: =E4*F4 -> 39.6 | K4: =IF(H4="","",1-F4/H4) -> 0
A5: 579901 | B5: 40878.358 | C5: Germany | D5: 37448 | E5: 12 | F5: 1.49 | G5: =_xlfn.XLOOKUP(D5,Catalog!$B$2:$B$4102,Catalog!$A$2:$A$4102,"NOT IN CATALOG") -> CERAMIC CAKE DESIGN SPOTTED MUG | H5: =_xlfn.IFNA(VLOOKUP(D5,Catalog!$B$2:$C$4102,2,FALSE()),"") -> 1.49 | I5: =HLOOKUP(C5,Regions!$B$1:$S$2,2,FALSE()) -> EU | J5: =E5*F5 -> 17.88 | K5: =IF(H5="","",1-F5/H5) -> 0
A6: 579901 | B6: 40878.358 | C6: Germany | D6: 37447 | E6: 12 | F6: 1.49 | G6: =_xlfn.XLOOKUP(D6,Catalog!$B$2:$B$4102,Catalog!$A$2:$A$4102,"NOT IN CATALOG") -> CERAMIC CAKE DESIGN SPOTTED PLATE | H6: =_xlfn.IFNA(VLOOKUP(D6,Catalog!$B$2:$C$4102,2,FALSE()),"") -> 1.49 | I6: =HLOOKUP(C6,Regions!$B$1:$S$2,2,FALSE()) -> EU | J6: =E6*F6 -> 17.88 | K6: =IF(H6="","",1-F6/H6) -> 0
A7: 579901 | B7: 40878.358 | C7: Germany | D7: 47559B | E7: 10 | F7: 1.25 | G7: =_xlfn.XLOOKUP(D7,Catalog!$B$2:$B$4102,Catalog!$A$2:$A$4102,"NOT IN CATALOG") -> TEA TIME OVEN GLOVE | H7: =_xlfn.IFNA(VLOOKUP(D7,Catalog!$B$2:$C$4102,2,FALSE()),"") -> 1.25 | I7: =HLOOKUP(C7,Regions!$B$1:$S$2,2,FALSE()) -> EU | J7: =E7*F7 -> 12.5 | K7: =IF(H7="","",1-F7/H7) -> 0
A8: 579901 | B8: 40878.358 | C8: Germany | D8: 47567B | E8: 3 | F8: 5.95 | G8: =_xlfn.XLOOKUP(D8,Catalog!$B$2:$B$4102,Catalog!$A$2:$A$4102,"NOT IN CATALOG") -> TEA TIME KITCHEN APRON | H8: =_xlfn.IFNA(VLOOKUP(D8,Catalog!$B$2:$C$4102,2,FALSE()),"") -> 5.95 | I8: =HLOOKUP(C8,Regions!$B$1:$S$2,2,FALSE()) -> EU | J8: =E8*F8 -> 17.85 | K8: =IF(H8="","",1-F8/H8) -> 0
A9: 579901 | B9: 40878.358 | C9: Germany | D9: 23578 | E9: 8 | F9: 1.95 | G9: =_xlfn.XLOOKUP(D9,Catalog!$B$2:$B$4102,Catalog!$A$2:$A$4102,"NOT IN CATALOG") -> NOT IN CATALOG | H9: =_xlfn.IFNA(VLOOKUP(D9,Catalog!$B$2:$C$4102,2,FALSE()),"") | I9: =HLOOKUP(C9,Regions!$B$1:$S$2,2,FALSE()) -> EU | J9: =E9*F9 -> 15.6 | K9: =IF(H9="","",1-F9/H9)
A10: 579901 | B10: 40878.358 | C10: Germany | D10: 22398 | E10: 12 | F10: 0.39 | G10: =_xlfn.XLOOKUP(D10,Catalog!$B$2:$B$4102,Catalog!$A$2:$A$4102,"NOT IN CATALOG") -> MAGNETS PACK OF 4 SWALLOWS | H10: =_xlfn.IFNA(VLOOKUP(D10,Catalog!$B$2:$C$4102,2,FALSE()),"") -> 1.25 | I10: =HLOOKUP(C10,Regions!$B$1:$S$2,2,FALSE()) -> EU | J10: =E10*F10 -> 4.68 | K10: =IF(H10="","",1-F10/H10) -> 0.688
A11: 579901 | B11: 40878.358 | C11: Germany | D11: POST | E11: 3 | F11: 18 | G11: =_xlfn.XLOOKUP(D11,Catalog!$B$2:$B$4102,Catalog!$A$2:$A$4102,"NOT IN CATALOG") -> POSTAGE | H11: =_xlfn.IFNA(VLOOKUP(D11,Catalog!$B$2:$C$4102,2,FALSE()),"") -> 18 | I11: =HLOOKUP(C11,Regions!$B$1:$S$2,2,FALSE()) -> EU | J11: =E11*F11 -> 54 | K11: =IF(H11="","",1-F11/H11) -> 0
A12: 579910 | B12: 40878.369 | C12: EIRE | D12: 85034C | E12: 24 | F12: 1.25 | G12: =_xlfn.XLOOKUP(D12,Catalog!$B$2:$B$4102,Catalog!$A$2:$A$4102,"NOT IN CATALOG") -> 3 ROSE MORRIS BOXED CANDLES | H12: =_xlfn.IFNA(VLOOKUP(D12,Catalog!$B$2:$C$4102,2,FALSE()),"") -> 4.25 | I12: =HLOOKUP(C12,Regions!$B$1:$S$2,2,FALSE()) -> EU | J12: =E12*F12 -> 30 | K12: =IF(H12="","",1-F12/H12) -> 0.70588235
A13: 579910 | B13: 40878.369 | C13: EIRE | D13: 23111 | E13: 2 | F13: 12.5 | G13: =_xlfn.XLOOKUP(D13,Catalog!$B$2:$B$4102,Catalog!$A$2:$A$4102,"NOT IN CATALOG") -> NOT IN CATALOG | H13: =_xlfn.IFNA(VLOOKUP(D13,Catalog!$B$2:$C$4102,2,FALSE()),"") | I13: =HLOOKUP(C13,Regions!$B$1:$S$2,2,FALSE()) -> EU | J13: =E13*F13 -> 25 | K13: =IF(H13="","",1-F13/H13)
... A1519: 581587 | B1519: 40886.535 | C1519: France | D1519: POST | E1519: 1 | F1519: 18 | G1519: =_xlfn.XLOOKUP(D1519,Catalog!$B$2:$B$4102,Catalog!$A$2:$A$4102,"NOT IN CATALOG") -> POSTAGE | H1519: =_xlfn.IFNA(VLOOKUP(D1519,Catalog!$B$2:$C$4102,2,FALSE()),"") -> 18 | I1519: =HLOOKUP(C1519,Regions!$B$1:$S$2,2,FALSE()) -> EU | J1519: =E1519*F1519 -> 18 | K1519: =IF(H1519="","",1-F1519/H1519) -> 0

Sheet Catalog
A1: Description | B1: StockCode | C1: ListPrice
A2: *Boombox Ipod Classic | B2: 21120 | C2: 16.98
A3: *USB Office Glitter Lamp | B3: 20739 | C3: 8.65
A4: *USB Office Mirror Ball | B4: 20954 | C4: 8.65
A5: 10 COLOUR SPACEBOY PEN | B5: 22418 | C5: 0.85
A6: 12 ASS ZINC CHRISTMAS DECORATIONS | B6: 35962 | C6: 2.1
A7: 12 COLOURED PARTY BALLOONS | B7: 22436 | C7: 0.65
A8: 12 DAISY PEGS IN WOOD BOX | B8: 21448 | C8: 1.65
A9: 12 EGG HOUSE PAINTED WOOD | B9: 22282 | C9: 12.75
A10: 12 IVORY ROSE PEG PLACE SETTINGS | B10: 21447 | C10: 1.25
A11: 12 MESSAGE CARDS WITH ENVELOPES | B11: 22906 | C11: 1.65
A12: 12 MINI TOADSTOOL PEGS | B12: 21440 | C12: 1.25
A13: 12 PENCIL SMALL TUBE WOODLAND | B13: 20973 | C13: 0.65
... A4102: ZINC WILLIE WINKIE CANDLE STICK | B4102: 84832 | C4102: 0.85

Sheet Regions
A1: Country | B1: Austria | C1: Belgium | D1: Channel Islands | E1: Denmark | F1: EIRE | G1: Finland | H1: France | I1: Germany | J1: Greece | K1: Iceland | L1: Italy | M1: Netherlands | N1: Norway | O1: Portugal | P1: Spain | Q1: Sweden | R1: USA | S1: United Kingdom
A2: Region | B2: EU | C2: EU | D2: Non-EU | E2: EU | F2: EU | G2: EU | H2: EU | I2: EU | J2: EU | K2: Non-EU | L2: EU | M2: EU | N2: Non-EU | O2: EU | P2: EU | Q2: EU | R2: Non-EU | S2: EU

Sheet Summary
A1: Chỉ số | B1: Giá trị
A2: Số dòng có mã không có trong Catalog | B2: =COUNTIF(Orders!G2:G1519,"NOT IN CATALOG") -> 440
A3: Số dòng bán thấp hơn giá niêm yết (DiscountPct > 0) | B3: =COUNTIF(Orders!K2:K1519,">0") -> 260
A4: Tổng doanh thu (GBP) | B4: =SUM(Orders!J2:J1519) -> 46188.59
A5: Doanh thu của mã không có trong Catalog (GBP) | B5: =SUMIFS(Orders!J2:J1519,Orders!G2:G1519,"NOT IN CATALOG") -> 17297.98
A6: Tỉ trọng doanh thu khách EU | B6: =SUMIFS(Orders!J2:J1519,Orders!I2:I1519,"EU")/B4 -> 0.91135993
A8: Mã hàng cần tra (nhập) | B8: 22423
A9: Giá niêm yết của mã ở ô B8 (INDEX/MATCH) | B9: =INDEX(Catalog!$C$2:$C$4102,MATCH(B8,Catalog!$B$2:$B$4102,0)) -> 12.75
